sematryx/__init__.py
sematryx/cli.py
sematryx/client.py
sematryx/exceptions.py
sematryx/models.py
sematryx-0.1.2.dist-info/METADATA
sematryx-0.1.2.dist-info/WHEEL
sematryx-0.1.2.dist-info/entry_points.txt
sematryx-0.1.2.dist-info/licenses/LICENSE
sematryx-0.1.2.dist-info/RECORD
