Metadata-Version: 2.4
Name: sematryx
Version: 0.1.2
Summary: Python SDK for Sematryx - AI-powered optimization that explains itself
Project-URL: Homepage, https://sematryx.com
Project-URL: Documentation, https://sematryx.com/docs
Project-URL: Repository, https://github.com/sematryx/sematryx-python
Project-URL: Changelog, https://github.com/sematryx/sematryx-python/releases
Author-email: Sematryx <support@sematryx.com>
License-Expression: MIT
License-File: LICENSE
Keywords: ai,constraint-optimization,explainable-ai,machine-learning,optimization,portfolio-optimization,supply-chain
Classifier: Development Status :: 4 - Beta
Classifier: Intended Audience :: Developers
Classifier: Intended Audience :: Science/Research
Classifier: License :: OSI Approved :: MIT License
Classifier: Operating System :: OS Independent
Classifier: Programming Language :: Python :: 3
Classifier: Programming Language :: Python :: 3.9
Classifier: Programming Language :: Python :: 3.10
Classifier: Programming Language :: Python :: 3.11
Classifier: Programming Language :: Python :: 3.12
Classifier: Topic :: Scientific/Engineering :: Artificial Intelligence
Classifier: Topic :: Scientific/Engineering :: Mathematics
Requires-Python: >=3.9
Requires-Dist: httpx>=0.24.0
Requires-Dist: pydantic>=2.0.0
Requires-Dist: rich>=13.0.0
Requires-Dist: typer>=0.9.0
Provides-Extra: dev
Requires-Dist: black>=23.0; extra == 'dev'
Requires-Dist: mypy>=1.0; extra == 'dev'
Requires-Dist: pytest-asyncio>=0.21; extra == 'dev'
Requires-Dist: pytest-cov>=4.0; extra == 'dev'
Requires-Dist: pytest>=7.0; extra == 'dev'
Requires-Dist: ruff>=0.1.0; extra == 'dev'
